[
    {
        "label": "grpc",
        "kind": 6,
        "isExtraImport": true,
        "importPath": "grpc",
        "description": "grpc",
        "detail": "grpc",
        "documentation": {}
    },
    {
        "label": "serializer",
        "kind": 6,
        "isExtraImport": true,
        "importPath": "serializer",
        "description": "serializer",
        "detail": "serializer",
        "documentation": {}
    },
    {
        "label": "socket",
        "kind": 6,
        "isExtraImport": true,
        "importPath": "socket",
        "description": "socket",
        "detail": "socket",
        "documentation": {}
    },
    {
        "label": "struct",
        "kind": 6,
        "isExtraImport": true,
        "importPath": "struct",
        "description": "struct",
        "detail": "struct",
        "documentation": {}
    },
    {
        "label": "threading",
        "kind": 6,
        "isExtraImport": true,
        "importPath": "threading",
        "description": "threading",
        "detail": "threading",
        "documentation": {}
    },
    {
        "label": "queue",
        "kind": 6,
        "isExtraImport": true,
        "importPath": "queue",
        "description": "queue",
        "detail": "queue",
        "documentation": {}
    },
    {
        "label": "enum",
        "kind": 6,
        "isExtraImport": true,
        "importPath": "enum",
        "description": "enum",
        "detail": "enum",
        "documentation": {}
    },
    {
        "label": "time",
        "kind": 6,
        "isExtraImport": true,
        "importPath": "time",
        "description": "time",
        "detail": "time",
        "documentation": {}
    },
    {
        "label": "gzip",
        "kind": 6,
        "isExtraImport": true,
        "importPath": "gzip",
        "description": "gzip",
        "detail": "gzip",
        "documentation": {}
    },
    {
        "label": "Iterator",
        "importPath": "typing",
        "description": "typing",
        "isExtraImport": true,
        "detail": "typing",
        "documentation": {}
    },
    {
        "label": "Dict",
        "importPath": "typing",
        "description": "typing",
        "isExtraImport": true,
        "detail": "typing",
        "documentation": {}
    },
    {
        "label": "Any",
        "importPath": "typing",
        "description": "typing",
        "isExtraImport": true,
        "detail": "typing",
        "documentation": {}
    },
    {
        "label": "Optional",
        "importPath": "typing",
        "description": "typing",
        "isExtraImport": true,
        "detail": "typing",
        "documentation": {}
    },
    {
        "label": "List",
        "importPath": "typing",
        "description": "typing",
        "isExtraImport": true,
        "detail": "typing",
        "documentation": {}
    },
    {
        "label": "Tuple",
        "importPath": "typing",
        "description": "typing",
        "isExtraImport": true,
        "detail": "typing",
        "documentation": {}
    },
    {
        "label": "traceback",
        "kind": 6,
        "isExtraImport": true,
        "importPath": "traceback",
        "description": "traceback",
        "detail": "traceback",
        "documentation": {}
    },
    {
        "label": "test_service_pb2",
        "kind": 6,
        "isExtraImport": true,
        "importPath": "test_service_pb2",
        "description": "test_service_pb2",
        "detail": "test_service_pb2",
        "documentation": {}
    },
    {
        "label": "test_service_pb2_grpc",
        "kind": 6,
        "isExtraImport": true,
        "importPath": "test_service_pb2_grpc",
        "description": "test_service_pb2_grpc",
        "detail": "test_service_pb2_grpc",
        "documentation": {}
    },
    {
        "label": "futures",
        "importPath": "concurrent",
        "description": "concurrent",
        "isExtraImport": true,
        "detail": "concurrent",
        "documentation": {}
    },
    {
        "label": "descriptor",
        "importPath": "google.protobuf",
        "description": "google.protobuf",
        "isExtraImport": true,
        "detail": "google.protobuf",
        "documentation": {}
    },
    {
        "label": "descriptor_pool",
        "importPath": "google.protobuf",
        "description": "google.protobuf",
        "isExtraImport": true,
        "detail": "google.protobuf",
        "documentation": {}
    },
    {
        "label": "runtime_version",
        "importPath": "google.protobuf",
        "description": "google.protobuf",
        "isExtraImport": true,
        "detail": "google.protobuf",
        "documentation": {}
    },
    {
        "label": "symbol_database",
        "importPath": "google.protobuf",
        "description": "google.protobuf",
        "isExtraImport": true,
        "detail": "google.protobuf",
        "documentation": {}
    },
    {
        "label": "builder",
        "importPath": "google.protobuf.internal",
        "description": "google.protobuf.internal",
        "isExtraImport": true,
        "detail": "google.protobuf.internal",
        "documentation": {}
    },
    {
        "label": "warnings",
        "kind": 6,
        "isExtraImport": true,
        "importPath": "warnings",
        "description": "warnings",
        "detail": "warnings",
        "documentation": {}
    },
    {
        "label": "TestClient",
        "kind": 6,
        "importPath": "tests.grpc.client1",
        "description": "tests.grpc.client1",
        "peekOfCode": "class TestClient:\n    def __init__(self, host='localhost:50051'):\n        self.channel = grpc.insecure_channel(host)\n        self.stub = self.channel.unary_unary(\n            '/TestService/SimpleTest',\n            request_serializer=lambda x: x,\n            response_deserializer=lambda x: x\n        )\n        self.stream_stub = self.channel.stream_stream(\n            '/TestService/StreamTest', ",
        "detail": "tests.grpc.client1",
        "documentation": {}
    },
    {
        "label": "client",
        "kind": 5,
        "importPath": "tests.grpc.client1",
        "description": "tests.grpc.client1",
        "peekOfCode": "client = TestClient()\nresult = client.simple_test(\"hello\", 123)\nprint(result)  # {'response': 'Processed: hello', 'received': True}\nclient.close()",
        "detail": "tests.grpc.client1",
        "documentation": {}
    },
    {
        "label": "result",
        "kind": 5,
        "importPath": "tests.grpc.client1",
        "description": "tests.grpc.client1",
        "peekOfCode": "result = client.simple_test(\"hello\", 123)\nprint(result)  # {'response': 'Processed: hello', 'received': True}\nclient.close()",
        "detail": "tests.grpc.client1",
        "documentation": {}
    },
    {
        "label": "StatusCode",
        "kind": 6,
        "importPath": "tests.grpc.client2",
        "description": "tests.grpc.client2",
        "peekOfCode": "class StatusCode(enum.IntEnum):\n    OK = 0\n    CANCELLED = 1\n    UNKNOWN = 2\n    INVALID_ARGUMENT = 3\n    DEADLINE_EXCEEDED = 4\n    NOT_FOUND = 5\n    ALREADY_EXISTS = 6\n    PERMISSION_DENIED = 7\n    RESOURCE_EXHAUSTED = 8",
        "detail": "tests.grpc.client2",
        "documentation": {}
    },
    {
        "label": "GRPCError",
        "kind": 6,
        "importPath": "tests.grpc.client2",
        "description": "tests.grpc.client2",
        "peekOfCode": "class GRPCError(Exception):\n    def __init__(self, code: StatusCode, message: str, details: bytes = b''):\n        self.code = code\n        self.message = message\n        self.details = details\n        super().__init__(f\"[Status {code.name} ({code.value})] {message}\")\n# ========== HTTP/2 Protocol Framework ==========\nclass FrameType(enum.IntEnum):\n    DATA = 0x0\n    HEADERS = 0x1",
        "detail": "tests.grpc.client2",
        "documentation": {}
    },
    {
        "label": "FrameType",
        "kind": 6,
        "importPath": "tests.grpc.client2",
        "description": "tests.grpc.client2",
        "peekOfCode": "class FrameType(enum.IntEnum):\n    DATA = 0x0\n    HEADERS = 0x1\n    PRIORITY = 0x2\n    RST_STREAM = 0x3\n    SETTINGS = 0x4\n    PUSH_PROMISE = 0x5\n    PING = 0x6\n    GOAWAY = 0x7\n    WINDOW_UPDATE = 0x8",
        "detail": "tests.grpc.client2",
        "documentation": {}
    },
    {
        "label": "FrameFlags",
        "kind": 6,
        "importPath": "tests.grpc.client2",
        "description": "tests.grpc.client2",
        "peekOfCode": "class FrameFlags(enum.IntEnum):\n    END_STREAM = 0x1\n    ACK = 0x1\n    END_HEADERS = 0x4\n    PADDED = 0x8\n# ========== HTTP/2 Frame Handler ==========\nclass HTTP2Frame:\n    @staticmethod\n    def pack_frame(frame_type: int, flags: int, stream_id: int, payload: bytes = b'') -> bytes:\n        length = len(payload)",
        "detail": "tests.grpc.client2",
        "documentation": {}
    },
    {
        "label": "HTTP2Frame",
        "kind": 6,
        "importPath": "tests.grpc.client2",
        "description": "tests.grpc.client2",
        "peekOfCode": "class HTTP2Frame:\n    @staticmethod\n    def pack_frame(frame_type: int, flags: int, stream_id: int, payload: bytes = b'') -> bytes:\n        length = len(payload)\n        header = struct.pack('>HBBBL', \n            length >> 8,\n            length & 0xFF,\n            frame_type,\n            flags,\n            stream_id & 0x7FFFFFFF",
        "detail": "tests.grpc.client2",
        "documentation": {}
    },
    {
        "label": "HPACK",
        "kind": 6,
        "importPath": "tests.grpc.client2",
        "description": "tests.grpc.client2",
        "peekOfCode": "class HPACK:\n    # RFC 7541 Static Table\n    STATIC_TABLE = [\n        (None, None),              # 0 - unused\n        (':authority', ''),        # 1\n        (':method', 'GET'),        # 2\n        (':method', 'POST'),       # 3\n        (':path', '/'),            # 4\n        (':path', '/index.html'),  # 5\n        (':scheme', 'http'),       # 6",
        "detail": "tests.grpc.client2",
        "documentation": {}
    },
    {
        "label": "FlowControl",
        "kind": 6,
        "importPath": "tests.grpc.client2",
        "description": "tests.grpc.client2",
        "peekOfCode": "class FlowControl:\n    def __init__(self, initial_window: int = 65535):\n        self.window_size = initial_window\n        self.lock = threading.Lock()\n    def consume(self, size: int) -> bool:\n        with self.lock:\n            if self.window_size >= size:\n                self.window_size -= size\n                return True\n            return False",
        "detail": "tests.grpc.client2",
        "documentation": {}
    },
    {
        "label": "StreamState",
        "kind": 6,
        "importPath": "tests.grpc.client2",
        "description": "tests.grpc.client2",
        "peekOfCode": "class StreamState(enum.Enum):\n    IDLE = 1\n    RESERVED_LOCAL = 2\n    RESERVED_REMOTE = 3\n    OPEN = 4\n    HALF_CLOSED_LOCAL = 5\n    HALF_CLOSED_REMOTE = 6\n    CLOSED = 7\nclass HTTP2Stream:\n    def __init__(self, stream_id: int, connection: 'HTTP2Connection'):",
        "detail": "tests.grpc.client2",
        "documentation": {}
    },
    {
        "label": "HTTP2Stream",
        "kind": 6,
        "importPath": "tests.grpc.client2",
        "description": "tests.grpc.client2",
        "peekOfCode": "class HTTP2Stream:\n    def __init__(self, stream_id: int, connection: 'HTTP2Connection'):\n        self.stream_id = stream_id\n        self.connection = connection\n        self.state = StreamState.IDLE\n        self.response_queue = queue.Queue()\n        self.flow_control = FlowControl(connection.settings.get(0x4, 65535))\n        self.headers = {}\n        self.trailers = {}\n        self.data = b''",
        "detail": "tests.grpc.client2",
        "documentation": {}
    },
    {
        "label": "HTTP2Connection",
        "kind": 6,
        "importPath": "tests.grpc.client2",
        "description": "tests.grpc.client2",
        "peekOfCode": "class HTTP2Connection:\n    def __init__(self, host: str, port: int):\n        self.host = host\n        self.port = port\n        self.socket = None\n        self.hpack = HPACK()\n        self.next_stream_id = 1\n        self.streams: Dict[int, HTTP2Stream] = {}\n        self.settings = {\n            0x1: 4096,    # HEADER_TABLE_SIZE",
        "detail": "tests.grpc.client2",
        "documentation": {}
    },
    {
        "label": "gRPCChannel",
        "kind": 6,
        "importPath": "tests.grpc.client2",
        "description": "tests.grpc.client2",
        "peekOfCode": "class gRPCChannel:\n    def __init__(self, host: str, port: int):\n        self.conn = HTTP2Connection(host, port)\n        self.conn.connect()\n    def _invoke(self, method: str, requests: Iterator[bytes], \n                timeout: Optional[float] = None, \n                metadata: Optional[Dict[str, str]] = None) -> Tuple[Dict[str, str], Iterator[bytes]]:\n        stream = self.conn.create_stream()\n        # Prepare headers\n        headers = {",
        "detail": "tests.grpc.client2",
        "documentation": {}
    },
    {
        "label": "TestStub",
        "kind": 6,
        "importPath": "tests.grpc.client2",
        "description": "tests.grpc.client2",
        "peekOfCode": "class TestStub:\n    def __init__(self, channel: gRPCChannel):\n        self.channel = channel\n    def simple_test(self, message: str, counter: int, **kwargs):\n        \"\"\"\n        Unary-Unary RPC: /TestService/SimpleTest\n        \"\"\"\n        request = serializer.requestToBytes({\"message\": message, \"counter\": counter})\n        response = self.channel.unary_unary('/TestService/SimpleTest', request, **kwargs)\n        return serializer.responseFromBytes(response)",
        "detail": "tests.grpc.client2",
        "documentation": {}
    },
    {
        "label": "TestClient",
        "kind": 6,
        "importPath": "tests.grpc.client2",
        "description": "tests.grpc.client2",
        "peekOfCode": "class TestClient:\n    def __init__(self, host='localhost', port=50051):\n        self.channel = gRPCChannel(host, port)\n        self.stub = TestStub(self.channel)\n    def simple_test(self, message, counter=1, timeout=None):\n        return self.stub.simple_test(message, counter, timeout=timeout)\n    def stream_test(self, messages, timeout=None):\n        return self.stub.stream_test(messages, timeout=timeout)\n    def ping(self):\n        return self.channel.ping()",
        "detail": "tests.grpc.client2",
        "documentation": {}
    },
    {
        "label": "generate_messages",
        "kind": 2,
        "importPath": "tests.grpc.client3",
        "description": "tests.grpc.client3",
        "peekOfCode": "def generate_messages():\n    \"\"\"Helper to generate a stream of requests.\"\"\"\n    messages = [\n        (\"First chunk\", 1),\n        (\"Second chunk\", 2),\n        (\"Third chunk\", 3),\n        (\"Fourth chunk\", 4),\n    ]\n    for msg, count in messages:\n        print(f\"Client Sending: {msg}, {count}\")",
        "detail": "tests.grpc.client3",
        "documentation": {}
    },
    {
        "label": "run",
        "kind": 2,
        "importPath": "tests.grpc.client3",
        "description": "tests.grpc.client3",
        "peekOfCode": "def run():\n    # connect to the server on localhost:50051\n    with grpc.insecure_channel('localhost:50051') as channel:\n        stub = pb2_grpc.TestServiceStub(channel)\n        print(\"-------------- Unary Call (SimpleTest) --------------\")\n        # Create a single request object\n        # Based on your server: request.message, request.counter\n        unary_request = pb2.TestRequest(message=\"Hello Server\", counter=100)\n        try:\n            unary_response = stub.SimpleTest(unary_request)",
        "detail": "tests.grpc.client3",
        "documentation": {}
    },
    {
        "label": "TestServicer",
        "kind": 6,
        "importPath": "tests.grpc.server",
        "description": "tests.grpc.server",
        "peekOfCode": "class TestServicer(pb2_grpc.TestServiceServicer):\n    def SimpleTest(self, request, context):\n        print(f\"Received: {request.message}, {request.counter}\")\n        return pb2.TestReply(\n            response=f\"Processed: {request.message}\", \n            received=True\n        )\n    def StreamTest(self, request_iterator, context):\n        for request in request_iterator:\n            print(f\"Stream received: {request.message}, {request.counter}\")",
        "detail": "tests.grpc.server",
        "documentation": {}
    },
    {
        "label": "serve",
        "kind": 2,
        "importPath": "tests.grpc.server",
        "description": "tests.grpc.server",
        "peekOfCode": "def serve():\n    server = grpc.server(futures.ThreadPoolExecutor(max_workers=10))\n    pb2_grpc.add_TestServiceServicer_to_server(TestServicer(), server)\n    server.add_insecure_port('0.0.0.0:50051')\n    server.start()\n    print(\"Server running on port 50051\")\n    server.wait_for_termination()\nif __name__ == '__main__':\n    serve()",
        "detail": "tests.grpc.server",
        "documentation": {}
    },
    {
        "label": "_sym_db",
        "kind": 5,
        "importPath": "tests.grpc.test_service_pb2",
        "description": "tests.grpc.test_service_pb2",
        "peekOfCode": "_sym_db = _symbol_database.Default()\nDESCRIPTOR = _descriptor_pool.Default().AddSerializedFile(b'\\n\\x12test_service.proto\\\"/\\n\\x0bTestRequest\\x12\\x0f\\n\\x07message\\x18\\x01 \\x01(\\t\\x12\\x0f\\n\\x07\\x63ounter\\x18\\x02 \\x01(\\x05\\\"/\\n\\tTestReply\\x12\\x10\\n\\x08response\\x18\\x01 \\x01(\\t\\x12\\x10\\n\\x08received\\x18\\x02 \\x01(\\x08\\x32\\x65\\n\\x0bTestService\\x12(\\n\\nSimpleTest\\x12\\x0c.TestRequest\\x1a\\n.TestReply\\\"\\x00\\x12,\\n\\nStreamTest\\x12\\x0c.TestRequest\\x1a\\n.TestReply\\\"\\x00(\\x01\\x30\\x01\\x62\\x06proto3')\n_globals = globals()\n_builder.BuildMessageAndEnumDescriptors(DESCRIPTOR, _globals)\n_builder.BuildTopDescriptorsAndMessages(DESCRIPTOR, 'test_service_pb2', _globals)\nif not _descriptor._USE_C_DESCRIPTORS:\n  DESCRIPTOR._loaded_options = None\n  _globals['_TESTREQUEST']._serialized_start=22\n  _globals['_TESTREQUEST']._serialized_end=69\n  _globals['_TESTREPLY']._serialized_start=71",
        "detail": "tests.grpc.test_service_pb2",
        "documentation": {}
    },
    {
        "label": "DESCRIPTOR",
        "kind": 5,
        "importPath": "tests.grpc.test_service_pb2",
        "description": "tests.grpc.test_service_pb2",
        "peekOfCode": "DESCRIPTOR = _descriptor_pool.Default().AddSerializedFile(b'\\n\\x12test_service.proto\\\"/\\n\\x0bTestRequest\\x12\\x0f\\n\\x07message\\x18\\x01 \\x01(\\t\\x12\\x0f\\n\\x07\\x63ounter\\x18\\x02 \\x01(\\x05\\\"/\\n\\tTestReply\\x12\\x10\\n\\x08response\\x18\\x01 \\x01(\\t\\x12\\x10\\n\\x08received\\x18\\x02 \\x01(\\x08\\x32\\x65\\n\\x0bTestService\\x12(\\n\\nSimpleTest\\x12\\x0c.TestRequest\\x1a\\n.TestReply\\\"\\x00\\x12,\\n\\nStreamTest\\x12\\x0c.TestRequest\\x1a\\n.TestReply\\\"\\x00(\\x01\\x30\\x01\\x62\\x06proto3')\n_globals = globals()\n_builder.BuildMessageAndEnumDescriptors(DESCRIPTOR, _globals)\n_builder.BuildTopDescriptorsAndMessages(DESCRIPTOR, 'test_service_pb2', _globals)\nif not _descriptor._USE_C_DESCRIPTORS:\n  DESCRIPTOR._loaded_options = None\n  _globals['_TESTREQUEST']._serialized_start=22\n  _globals['_TESTREQUEST']._serialized_end=69\n  _globals['_TESTREPLY']._serialized_start=71\n  _globals['_TESTREPLY']._serialized_end=118",
        "detail": "tests.grpc.test_service_pb2",
        "documentation": {}
    },
    {
        "label": "_globals",
        "kind": 5,
        "importPath": "tests.grpc.test_service_pb2",
        "description": "tests.grpc.test_service_pb2",
        "peekOfCode": "_globals = globals()\n_builder.BuildMessageAndEnumDescriptors(DESCRIPTOR, _globals)\n_builder.BuildTopDescriptorsAndMessages(DESCRIPTOR, 'test_service_pb2', _globals)\nif not _descriptor._USE_C_DESCRIPTORS:\n  DESCRIPTOR._loaded_options = None\n  _globals['_TESTREQUEST']._serialized_start=22\n  _globals['_TESTREQUEST']._serialized_end=69\n  _globals['_TESTREPLY']._serialized_start=71\n  _globals['_TESTREPLY']._serialized_end=118\n  _globals['_TESTSERVICE']._serialized_start=120",
        "detail": "tests.grpc.test_service_pb2",
        "documentation": {}
    },
    {
        "label": "TestServiceStub",
        "kind": 6,
        "importPath": "tests.grpc.test_service_pb2_grpc",
        "description": "tests.grpc.test_service_pb2_grpc",
        "peekOfCode": "class TestServiceStub(object):\n    \"\"\"Missing associated documentation comment in .proto file.\"\"\"\n    def __init__(self, channel):\n        \"\"\"Constructor.\n        Args:\n            channel: A grpc.Channel.\n        \"\"\"\n        self.SimpleTest = channel.unary_unary(\n                '/TestService/SimpleTest',\n                request_serializer=test__service__pb2.TestRequest.SerializeToString,",
        "detail": "tests.grpc.test_service_pb2_grpc",
        "documentation": {}
    },
    {
        "label": "TestServiceServicer",
        "kind": 6,
        "importPath": "tests.grpc.test_service_pb2_grpc",
        "description": "tests.grpc.test_service_pb2_grpc",
        "peekOfCode": "class TestServiceServicer(object):\n    \"\"\"Missing associated documentation comment in .proto file.\"\"\"\n    def SimpleTest(self, request, context):\n        \"\"\"Missing associated documentation comment in .proto file.\"\"\"\n        context.set_code(grpc.StatusCode.UNIMPLEMENTED)\n        context.set_details('Method not implemented!')\n        raise NotImplementedError('Method not implemented!')\n    def StreamTest(self, request_iterator, context):\n        \"\"\"Missing associated documentation comment in .proto file.\"\"\"\n        context.set_code(grpc.StatusCode.UNIMPLEMENTED)",
        "detail": "tests.grpc.test_service_pb2_grpc",
        "documentation": {}
    },
    {
        "label": "TestService",
        "kind": 6,
        "importPath": "tests.grpc.test_service_pb2_grpc",
        "description": "tests.grpc.test_service_pb2_grpc",
        "peekOfCode": "class TestService(object):\n    \"\"\"Missing associated documentation comment in .proto file.\"\"\"\n    @staticmethod\n    def SimpleTest(request,\n            target,\n            options=(),\n            channel_credentials=None,\n            call_credentials=None,\n            insecure=False,\n            compression=None,",
        "detail": "tests.grpc.test_service_pb2_grpc",
        "documentation": {}
    },
    {
        "label": "add_TestServiceServicer_to_server",
        "kind": 2,
        "importPath": "tests.grpc.test_service_pb2_grpc",
        "description": "tests.grpc.test_service_pb2_grpc",
        "peekOfCode": "def add_TestServiceServicer_to_server(servicer, server):\n    rpc_method_handlers = {\n            'SimpleTest': grpc.unary_unary_rpc_method_handler(\n                    servicer.SimpleTest,\n                    request_deserializer=test__service__pb2.TestRequest.FromString,\n                    response_serializer=test__service__pb2.TestReply.SerializeToString,\n            ),\n            'StreamTest': grpc.stream_stream_rpc_method_handler(\n                    servicer.StreamTest,\n                    request_deserializer=test__service__pb2.TestRequest.FromString,",
        "detail": "tests.grpc.test_service_pb2_grpc",
        "documentation": {}
    },
    {
        "label": "GRPC_GENERATED_VERSION",
        "kind": 5,
        "importPath": "tests.grpc.test_service_pb2_grpc",
        "description": "tests.grpc.test_service_pb2_grpc",
        "peekOfCode": "GRPC_GENERATED_VERSION = '1.70.0'\nGRPC_VERSION = grpc.__version__\n_version_not_supported = False\ntry:\n    from grpc._utilities import first_version_is_lower\n    _version_not_supported = first_version_is_lower(GRPC_VERSION, GRPC_GENERATED_VERSION)\nexcept ImportError:\n    _version_not_supported = True\nif _version_not_supported:\n    raise RuntimeError(",
        "detail": "tests.grpc.test_service_pb2_grpc",
        "documentation": {}
    },
    {
        "label": "GRPC_VERSION",
        "kind": 5,
        "importPath": "tests.grpc.test_service_pb2_grpc",
        "description": "tests.grpc.test_service_pb2_grpc",
        "peekOfCode": "GRPC_VERSION = grpc.__version__\n_version_not_supported = False\ntry:\n    from grpc._utilities import first_version_is_lower\n    _version_not_supported = first_version_is_lower(GRPC_VERSION, GRPC_GENERATED_VERSION)\nexcept ImportError:\n    _version_not_supported = True\nif _version_not_supported:\n    raise RuntimeError(\n        f'The grpc package installed is at version {GRPC_VERSION},'",
        "detail": "tests.grpc.test_service_pb2_grpc",
        "documentation": {}
    },
    {
        "label": "_version_not_supported",
        "kind": 5,
        "importPath": "tests.grpc.test_service_pb2_grpc",
        "description": "tests.grpc.test_service_pb2_grpc",
        "peekOfCode": "_version_not_supported = False\ntry:\n    from grpc._utilities import first_version_is_lower\n    _version_not_supported = first_version_is_lower(GRPC_VERSION, GRPC_GENERATED_VERSION)\nexcept ImportError:\n    _version_not_supported = True\nif _version_not_supported:\n    raise RuntimeError(\n        f'The grpc package installed is at version {GRPC_VERSION},'\n        + f' but the generated code in test_service_pb2_grpc.py depends on'",
        "detail": "tests.grpc.test_service_pb2_grpc",
        "documentation": {}
    }
]